{"id":"santa-isabel-do-rio-negro-brazil","name":"Santa Isabel do Rio Negro, Brazil","country":"Brazil","cables":[{"id":"projeto-amaznia-conectada-pac-02","name":"Projeto Amazônia Conectada (PAC 02)","rfs_year":2021,"is_planned":false,"landing_points":["barcelos-brazil","moura-brazil","novo-airo-brazil","santa-isabel-do-rio-negro-brazil","so-gabriel-da-cachoeira-brazil"]}],"landing_points":["novo-airo-brazil","moura-brazil","barcelos-brazil","santa-isabel-do-rio-negro-brazil","so-gabriel-da-cachoeira-brazil"]}
