{"id":"singapore-singapore","name":"Singapore, Singapore","country":"Singapore","cables":[{"id":"asia-connect-cable-1-acc-1","name":"Asia Connect Cable-1 (ACC-1)","rfs_year":2028,"is_planned":true,"landing_points":["alupang-guam","batam-indonesia","darwin-nt-australia","davao-philippines","dili-timor-leste","hermosa-beach-ca-united-states","jakarta-indonesia","makassar-indonesia","manado-indonesia","singapore-singapore"]},{"id":"hawaiki-nui-1","name":"Hawaiki Nui 1","rfs_year":2027,"is_planned":true,"landing_points":["batam-indonesia","brisbane-qld-australia","darwin-nt-australia","dili-timor-leste","honiara-solomon-islands","jakarta-indonesia","port-moresby-papua-new-guinea","singapore-singapore","sydney-nsw-australia"]}],"landing_points":["singapore-singapore","batam-indonesia","jakarta-indonesia","darwin-nt-australia","brisbane-qld-australia","sydney-nsw-australia","alupang-guam","makassar-indonesia","dili-timor-leste","manado-indonesia","davao-philippines","hermosa-beach-ca-united-states","port-moresby-papua-new-guinea","honiara-solomon-islands"]}
